README.md
setup.cfg
setup.py
IGMods/__init__.py
IGMods/bot_instagram.py
IGMods/bot_postgres.py
IGMods/postgres_communication.py
IGMods/postgres_quaries.py
IGMods/session_data.py
IGMods/test_environment.py
igMod.egg-info/PKG-INFO
igMod.egg-info/SOURCES.txt
igMod.egg-info/dependency_links.txt
igMod.egg-info/not-zip-safe
igMod.egg-info/requires.txt
igMod.egg-info/top_level.txt