Metadata-Version: 1.1
Name: igMod
Version: 0.1
Summary: igMods bc4
Home-page: UNKNOWN
Author: bc4
Author-email: UNKNOWN
License: UNKNOWN
Download-URL: https://github.com/bymathears/bc4/tree/0.1/igMods
Platform: UNKNOWN
